tvtk_utils.py
tvtk_visualiser.py
tvtk_visualiser-1.0.2.dist-info/DESCRIPTION.rst
tvtk_visualiser-1.0.2.dist-info/METADATA
tvtk_visualiser-1.0.2.dist-info/RECORD
tvtk_visualiser-1.0.2.dist-info/WHEEL
tvtk_visualiser-1.0.2.dist-info/metadata.json
tvtk_visualiser-1.0.2.dist-info/top_level.txt
